gamercon_async/__init__.py
gamercon_async/gamercon_async.py
gamercon_async-1.0.7.dist-info/METADATA
gamercon_async-1.0.7.dist-info/WHEEL
gamercon_async-1.0.7.dist-info/top_level.txt
gamercon_async-1.0.7.dist-info/RECORD
