Metadata-Version: 2.1
Name: gamercon-async
Version: 1.0.7
Summary: An async rcon protocol for video games.
Home-page: https://github.com/dkoz/gamercon-async
Author: dkoz
Author-email: koz@beskor.net
Requires-Python: >=3.11
